fastapi_amis_admin/__init__.py
fastapi_amis_admin/admin/__init__.py
fastapi_amis_admin/admin/admin.py
fastapi_amis_admin/admin/handlers.py
fastapi_amis_admin/admin/parser.py
fastapi_amis_admin/admin/settings.py
fastapi_amis_admin/admin/site.py
fastapi_amis_admin/admin/extensions/__init__.py
fastapi_amis_admin/admin/extensions/admin.py
fastapi_amis_admin/admin/extensions/schemas.py
fastapi_amis_admin/admin/extensions/utils.py
fastapi_amis_admin/amis/README.md
fastapi_amis_admin/amis/__init__.py
fastapi_amis_admin/amis/components.py
fastapi_amis_admin/amis/constants.py
fastapi_amis_admin/amis/types.py
fastapi_amis_admin/amis/utils.py
fastapi_amis_admin/amis/templates/app.html
fastapi_amis_admin/amis/templates/page.html
fastapi_amis_admin/crud/README.md
fastapi_amis_admin/crud/__init__.py
fastapi_amis_admin/crud/_sqlalchemy.py
fastapi_amis_admin/crud/_sqlmodel.py
fastapi_amis_admin/crud/base.py
fastapi_amis_admin/crud/parser.py
fastapi_amis_admin/crud/schema.py
fastapi_amis_admin/crud/utils.py
fastapi_amis_admin/globals/__init__.py
fastapi_amis_admin/globals/_db.py
fastapi_amis_admin/globals/_sites.py
fastapi_amis_admin/globals/core.py
fastapi_amis_admin/globals/deps.py
fastapi_amis_admin/locale/de_DE/LC_MESSAGES/messages.mo
fastapi_amis_admin/locale/de_DE/LC_MESSAGES/messages.po
fastapi_amis_admin/locale/zh_CN/LC_MESSAGES/messages.mo
fastapi_amis_admin/locale/zh_CN/LC_MESSAGES/messages.po
fastapi_amis_admin/models/__init__.py
fastapi_amis_admin/models/_enums.py
fastapi_amis_admin/models/_sqltypes.py
fastapi_amis_admin/models/fields.py
fastapi_amis_admin/utils/__init__.py
fastapi_amis_admin/utils/functools.py
fastapi_amis_admin/utils/pydantic.py
fastapi_amis_admin/utils/translation.py
fastapi_amis_admin-0.7.0.dist-info/LICENSE
fastapi_amis_admin-0.7.0.dist-info/WHEEL
fastapi_amis_admin-0.7.0.dist-info/METADATA
fastapi_amis_admin-0.7.0.dist-info/RECORD
