Metadata-Version: 2.1
Name: fastapi_amis_admin
Version: 0.7.0
Summary: FastAPI-Amis-Admin is a high-performance, efficient and easily extensible FastAPI admin framework. Inspired by Django-admin, and has as many powerful functions as Django-admin. 
Keywords: fastapi,fastapi-admin,fastapi-amis-admin,django-admin,sqlmodel,sqlalchemy
Author-email: Atomi <1456417373@qq.com>
Maintainer-email: Atomi <1456417373@qq.com>
Requires-Python: >=3.8
Classifier: Framework :: FastAPI
Classifier: Environment :: Web Environment
Classifier: Topic :: System :: Systems Administration
Classifier: License :: OSI Approved :: Apache Software License
Classifier: Operating System :: OS Independent
Classifier: Programming Language :: Python :: 3
Classifier: Programming Language :: Python :: 3.7
Classifier: Programming Language :: Python :: 3.8
Classifier: Programming Language :: Python :: 3.9
Classifier: Programming Language :: Python :: 3.10
Classifier: Programming Language :: Python :: 3.11
Requires-Dist: fastapi>=0.103.2
Requires-Dist: sqlmodel>=0.0.14,<0.1.0
Requires-Dist: python-multipart>=0.0.5
Requires-Dist: sqlalchemy-database>=0.1.1,<0.2.0
Requires-Dist: aiofiles>=0.17.0
Requires-Dist: fastapi-amis-admin-cli>=0.2.1,<0.3.0 ; extra == "cli"
Requires-Dist: pre-commit>=2.20.0 ; extra == "dev"
Requires-Dist: ruff>=0.0.261 ; extra == "dev"
Requires-Dist: uvicorn[standard] >=0.19.0,<1.0 ; extra == "standard"
Requires-Dist: fastapi-amis-admin-cli>=0.2.1,<0.3.0 ; extra == "standard"
Requires-Dist: uvicorn[standard] >=0.19.0,<1.0 ; extra == "test"
Requires-Dist: fastapi-amis-admin-cli>=0.2.1,<0.3.0 ; extra == "test"
Requires-Dist: pytest >=6.2.4 ; extra == "test"
Requires-Dist: aiosqlite>=0.15.0 ; extra == "test"
Requires-Dist: pytest-asyncio>=0.17 ; extra == "test"
Requires-Dist: httpx>=0.24.0,<1.0 ; extra == "test"
Requires-Dist: jinja2 >=2.11.2,<4.0.0 ; extra == "test"
Requires-Dist: ujson>=4.0.1 ; extra == "test"
Requires-Dist: requests>=2.28.1 ; extra == "test"
Requires-Dist: pydantic-settings>=2.0.0 ; extra == "test"
Project-URL: Documentation, http://docs.amis.work/
Project-URL: Source, https://github.com/amisadmin/fastapi_amis_admin
Provides-Extra: cli
Provides-Extra: dev
Provides-Extra: standard
Provides-Extra: test
